RegistratorAutomationService/__init__.py
RegistratorAutomationService/__main__.py
RegistratorAutomationService/const.py
RegistratorAutomationService/service.py
pih_rgst_auto-0.14.1.dist-info/METADATA
pih_rgst_auto-0.14.1.dist-info/WHEEL
pih_rgst_auto-0.14.1.dist-info/entry_points.txt
pih_rgst_auto-0.14.1.dist-info/top_level.txt
pih_rgst_auto-0.14.1.dist-info/RECORD
