Metadata-Version: 2.1
Name: pih-rgst_auto
Version: 0.14.1
Summary: PIH Registrator Automation service package
Home-page: https://pacifichosp.com/
Author: Nikita Karachentsev
Author-email: it@pacifichosp.com
License: MIT
Requires-Dist: ipih
Requires-Dist: pih-mio
